{"nodes": [{"id": "tasks_actions_toggleTaskAction", "label": "toggleTaskAction", "file_type": "code", "source_file": "web/src/app/actions/tasks.ts", "source_location": "L14", "source_url": null, "captured_at": null, "author": null, "contributor": null}, {"id": "tasks_actions_deferTaskAction", "label": "deferTaskAction", "file_type": "code", "source_file": "web/src/app/actions/tasks.ts", "source_location": "L27", "source_url": null, "captured_at": null, "author": null, "contributor": null}, {"id": "tasks_actions_failTaskAction", "label": "failTaskAction", "file_type": "code", "source_file": "web/src/app/actions/tasks.ts", "source_location": "L35", "source_url": null, "captured_at": null, "author": null, "contributor": null}, {"id": "tasks_actions_completeTaskByAction", "label": "completeTaskByAction", "file_type": "code", "source_file": "web/src/app/actions/tasks.ts", "source_location": "L52", "source_url": null, "captured_at": null, "author": null, "contributor": null}, {"id": "tasks_actions_addTaskAction", "label": "addTaskAction", "file_type": "code", "source_file": "web/src/app/actions/tasks.ts", "source_location": "L61", "source_url": null, "captured_at": null, "author": null, "contributor": null}], "edges": [{"source": "tasks_actions_toggleTaskAction", "target": "tasks_repo_setTaskStatus", "relation": "calls", "confidence": "EXTRACTED", "confidence_score": 1.0, "source_file": "web/src/app/actions/tasks.ts", "source_location": null, "weight": 1.0}, {"source": "tasks_actions_toggleTaskAction", "target": "revalidate_revalidateDashboard", "relation": "calls", "confidence": "EXTRACTED", "confidence_score": 1.0, "source_file": "web/src/app/actions/tasks.ts", "source_location": null, "weight": 1.0}, {"source": "tasks_actions_deferTaskAction", "target": "tasks_repo_deferTask", "relation": "calls", "confidence": "EXTRACTED", "confidence_score": 1.0, "source_file": "web/src/app/actions/tasks.ts", "source_location": null, "weight": 1.0}, {"source": "tasks_actions_deferTaskAction", "target": "revalidate_revalidateDashboard", "relation": "calls", "confidence": "EXTRACTED", "confidence_score": 1.0, "source_file": "web/src/app/actions/tasks.ts", "source_location": null, "weight": 1.0}, {"source": "tasks_actions_failTaskAction", "target": "tasks_repo_setTaskStatus", "relation": "calls", "confidence": "EXTRACTED", "confidence_score": 1.0, "source_file": "web/src/app/actions/tasks.ts", "source_location": null, "weight": 1.0}, {"source": "tasks_actions_failTaskAction", "target": "revalidate_revalidateDashboard", "relation": "calls", "confidence": "EXTRACTED", "confidence_score": 1.0, "source_file": "web/src/app/actions/tasks.ts", "source_location": null, "weight": 1.0}, {"source": "tasks_actions_completeTaskByAction", "target": "tasks_repo_completeTaskBy", "relation": "calls", "confidence": "EXTRACTED", "confidence_score": 1.0, "source_file": "web/src/app/actions/tasks.ts", "source_location": null, "weight": 1.0}, {"source": "tasks_actions_completeTaskByAction", "target": "revalidate_revalidateDashboard", "relation": "calls", "confidence": "EXTRACTED", "confidence_score": 1.0, "source_file": "web/src/app/actions/tasks.ts", "source_location": null, "weight": 1.0}, {"source": "tasks_actions_addTaskAction", "target": "tasks_repo_createTask", "relation": "calls", "confidence": "EXTRACTED", "confidence_score": 1.0, "source_file": "web/src/app/actions/tasks.ts", "source_location": null, "weight": 1.0}, {"source": "tasks_actions_addTaskAction", "target": "revalidate_revalidateDashboard", "relation": "calls", "confidence": "EXTRACTED", "confidence_score": 1.0, "source_file": "web/src/app/actions/tasks.ts", "source_location": null, "weight": 1.0}, {"source": "tasks_actions_toggleTaskAction", "target": "tasks_repo_setTaskStatus", "relation": "references", "confidence": "EXTRACTED", "confidence_score": 1.0, "source_file": "web/src/app/actions/tasks.ts", "source_location": "L4-6", "weight": 1.0}], "hyperedges": []}