{"nodes": [{"id": "dates_dayBounds", "label": "dayBounds() (dates lib)", "file_type": "code", "source_file": "web/src/lib/dates.ts", "source_location": null, "source_url": null, "captured_at": null, "author": null, "contributor": null}, {"id": "dates_localDateKey", "label": "localDateKey() (dates lib)", "file_type": "code", "source_file": "web/src/lib/dates.ts", "source_location": null, "source_url": null, "captured_at": null, "author": null, "contributor": null}, {"id": "dates_currentWeekBounds", "label": "currentWeekBounds", "file_type": "code", "source_file": "web/src/lib/dates.ts", "source_location": "L6", "source_url": null, "captured_at": null, "author": null, "contributor": null}, {"id": "dates_dayBounds", "label": "dayBounds", "file_type": "code", "source_file": "web/src/lib/dates.ts", "source_location": "L11", "source_url": null, "captured_at": null, "author": null, "contributor": null}, {"id": "dates_formatTime", "label": "formatTime", "file_type": "code", "source_file": "web/src/lib/dates.ts", "source_location": "L22", "source_url": null, "captured_at": null, "author": null, "contributor": null}, {"id": "dates_addDays", "label": "addDays", "file_type": "code", "source_file": "web/src/lib/dates.ts", "source_location": "L29", "source_url": null, "captured_at": null, "author": null, "contributor": null}, {"id": "dates_mondayOf", "label": "mondayOf", "file_type": "code", "source_file": "web/src/lib/dates.ts", "source_location": "L36", "source_url": null, "captured_at": null, "author": null, "contributor": null}, {"id": "dates_weekBoundsOf", "label": "weekBoundsOf", "file_type": "code", "source_file": "web/src/lib/dates.ts", "source_location": "L46", "source_url": null, "captured_at": null, "author": null, "contributor": null}, {"id": "dates_localDateKey", "label": "localDateKey", "file_type": "code", "source_file": "web/src/lib/dates.ts", "source_location": "L57", "source_url": null, "captured_at": null, "author": null, "contributor": null}, {"id": "dates_currentWeekBounds", "label": "currentWeekBounds", "file_type": "code", "source_file": "web/src/lib/dates.ts", "source_location": null, "source_url": null, "captured_at": null, "author": null, "contributor": null}, {"id": "dates_dayBounds", "label": "dayBounds", "file_type": "code", "source_file": "web/src/lib/dates.ts", "source_location": null, "source_url": null, "captured_at": null, "author": null, "contributor": null}, {"id": "dates_formatTime", "label": "formatTime", "file_type": "code", "source_file": "web/src/lib/dates.ts", "source_location": null, "source_url": null, "captured_at": null, "author": null, "contributor": null}, {"id": "dates_addDays", "label": "addDays", "file_type": "code", "source_file": "web/src/lib/dates.ts", "source_location": null, "source_url": null, "captured_at": null, "author": null, "contributor": null}, {"id": "dates_localDateKey", "label": "localDateKey", "file_type": "code", "source_file": "web/src/lib/dates.ts", "source_location": null, "source_url": null, "captured_at": null, "author": null, "contributor": null}, {"id": "dates_mondayOf", "label": "mondayOf", "file_type": "code", "source_file": "web/src/lib/dates.ts", "source_location": null, "source_url": null, "captured_at": null, "author": null, "contributor": null}, {"id": "dates_currentWeekBounds", "label": "currentWeekBounds", "file_type": "code", "source_file": "web/src/lib/dates.ts", "source_location": null, "source_url": null, "captured_at": null, "author": null, "contributor": null}, {"id": "dates_addDays", "label": "addDays", "file_type": "code", "source_file": "web/src/lib/dates.ts", "source_location": null, "source_url": null, "captured_at": null, "author": null, "contributor": null}, {"id": "dates_dayBounds", "label": "dayBounds", "file_type": "code", "source_file": "web/src/lib/dates.ts", "source_location": null, "source_url": null, "captured_at": null, "author": null, "contributor": null}, {"id": "dates_addDays", "label": "addDays", "file_type": "code", "source_file": "web/src/lib/dates.ts", "source_location": null, "source_url": null, "captured_at": null, "author": null, "contributor": null}, {"id": "dates_mondayOf", "label": "mondayOf", "file_type": "code", "source_file": "web/src/lib/dates.ts", "source_location": null, "source_url": null, "captured_at": null, "author": null, "contributor": null}, {"id": "dates_dayBounds", "label": "dayBounds", "file_type": "code", "source_file": "web/src/lib/dates.ts", "source_location": null, "source_url": null, "captured_at": null, "author": null, "contributor": null}, {"id": "dates_weekBoundsOf", "label": "weekBoundsOf", "file_type": "code", "source_file": "web/src/lib/dates.ts", "source_location": null, "source_url": null, "captured_at": null, "author": null, "contributor": null}, {"id": "dates_currentWeekBounds", "label": "currentWeekBounds", "file_type": "code", "source_file": "web/src/lib/dates.ts", "source_location": null, "source_url": null, "captured_at": null, "author": null, "contributor": null}, {"id": "dates_dayBounds", "label": "dayBounds", "file_type": "code", "source_file": "web/src/lib/dates.ts", "source_location": null, "source_url": null, "captured_at": null, "author": null, "contributor": null}, {"id": "mondayOf", "label": "mondayOf()", "file_type": "code", "source_file": "web/src/lib/dates.ts", "source_location": null, "source_url": null, "captured_at": null, "author": null, "contributor": null}, {"id": "localDateKey", "label": "localDateKey()", "file_type": "code", "source_file": "web/src/lib/dates.ts", "source_location": null, "source_url": null, "captured_at": null, "author": null, "contributor": null}, {"id": "weekBoundsOf", "label": "weekBoundsOf()", "file_type": "code", "source_file": "web/src/lib/dates.ts", "source_location": null, "source_url": null, "captured_at": null, "author": null, "contributor": null}], "edges": [{"source": "dates_weekBoundsOf", "target": "dates_mondayOf", "relation": "calls", "confidence": "EXTRACTED", "confidence_score": 1.0, "source_file": "web/src/lib/dates.ts", "source_location": "L47", "weight": 1.0}, {"source": "dates_weekBoundsOf", "target": "dates_addDays", "relation": "calls", "confidence": "EXTRACTED", "confidence_score": 1.0, "source_file": "web/src/lib/dates.ts", "source_location": "L48", "weight": 1.0}, {"source": "dates_currentWeekBounds", "target": "dates_weekBoundsOf", "relation": "calls", "confidence": "EXTRACTED", "confidence_score": 1.0, "source_file": "web/src/lib/dates.ts", "source_location": "L7", "weight": 1.0}, {"source": "dates_dayBounds", "target": "capacity_activeDayWindow", "relation": "semantically_similar_to", "confidence": "INFERRED", "confidence_score": 0.75, "source_file": "web/src/lib/dates.ts", "source_location": "L11", "weight": 1.0}], "hyperedges": []}