{"nodes": [{"id": "types_Situation", "label": "Situation", "file_type": "code", "source_file": "web/src/lib/baby/types.ts", "source_location": "L5", "source_url": null, "captured_at": null, "author": null, "contributor": null}, {"id": "types_AgeBand", "label": "AgeBand", "file_type": "code", "source_file": "web/src/lib/baby/types.ts", "source_location": "L13", "source_url": null, "captured_at": null, "author": null, "contributor": null}, {"id": "types_Warmth", "label": "Warmth", "file_type": "code", "source_file": "web/src/lib/baby/types.ts", "source_location": "L15", "source_url": null, "captured_at": null, "author": null, "contributor": null}, {"id": "types_ClothingAdvice", "label": "ClothingAdvice", "file_type": "code", "source_file": "web/src/lib/baby/types.ts", "source_location": "L17", "source_url": null, "captured_at": null, "author": null, "contributor": null}, {"id": "types_UvLevel", "label": "UvLevel", "file_type": "code", "source_file": "web/src/lib/baby/types.ts", "source_location": "L24", "source_url": null, "captured_at": null, "author": null, "contributor": null}, {"id": "types_UvAdvice", "label": "UvAdvice", "file_type": "code", "source_file": "web/src/lib/baby/types.ts", "source_location": "L26", "source_url": null, "captured_at": null, "author": null, "contributor": null}], "edges": [], "hyperedges": [{"id": "baby_advice_pipeline", "label": "Baby weather-aware advice pipeline (age + temp + UV \u2192 clothing/UV advice)", "nodes": ["baby_babyAge", "clothing_recommendClothing", "uv_uvAdvice", "types_AgeBand"], "relation": "participate_in", "confidence": "INFERRED", "confidence_score": 0.85, "source_file": "web/src/lib/baby/types.ts"}]}